[
    {
        "id": "1",
        "img": "https://static.toiimg.com/thumb/msid-86989484,imgsize-124884,width-400,resizemode-4/86989484.jpg",
        "content": "Yessss....! Team India new jersy for ICC Cricket World Cup 2023",
        "time": "23 min ago"
    },
    {
        "id": "2",
        "img": "https://c.ndtvimg.com/2022-06/lou4uib8_brendon-mccullum-afp_625x300_21_June_22.jpg",
        "content": "England coach Brendon McCullum labelled 'Bazball' a silly term",
        "time": "2 hours ago"
    },
    {
        "id": "3",
        "img": "https://c.ndtvimg.com/2022-01/e7mo133_quinton-de-kock-afp_625x300_23_January_22.jpg",
        "content": "India vs South Africa, 3rd ODI: Quinton de Kock registered his 17th ODI ton in Cape Town",
        "time": "5 hours ago"
    },
    {
        "id": "4",
        "img": "https://c.ndtvimg.com/2019-04/e1i28ueo_ms-dhoni-virat-kohli-bcciipl_240x180_22_April_19.jpg",
        "content": "IPL 2022: Former Australia cricketer Adam Gilchrist on Saturday asked people about IPL.",
        "time": "9 hours ago"
    },
    {
        "id": "5",
        "img": "https://c.ndtvimg.com/2022-07/cael265_jasprit-bumrah-afp_625x300_13_July_22.jpg",
        "content": "Jasprit Bumrah put on a sensational bowling display in the first ODI",
        "time": "1 day ago"
    }
]